{
  "main": {
    "id": "ac892cc912605614",
    "type": "split",
    "children": [
      {
        "id": "9c67d180ceeecff9",
        "type": "tabs",
        "children": [
          {
            "id": "00e9bba255646ea2",
            "type": "leaf",
            "state": {
              "type": "markdown",
              "state": {
                "file": "mathematics/stochastics/joint distribution.md",
                "mode": "source",
                "source": false
              }
            }
          },
          {
            "id": "63374a1eca3db97d",
            "type": "leaf",
            "state": {
              "type": "markdown",
              "state": {
                "file": "mathematics/stochastics/stochastic independent.md",
                "mode": "source",
                "source": false
              }
            }
          },
          {
            "id": "b071b1e8532c49a4",
            "type": "leaf",
            "state": {
              "type": "markdown",
              "state": {
                "file": "mathematics/stochastics/probability space.md",
                "mode": "source",
                "source": false
              }
            }
          },
          {
            "id": "e054fb07fc0bc717",
            "type": "leaf",
            "state": {
              "type": "markdown",
              "state": {
                "file": "mathematics/basics/linear algebra/matrix.md",
                "mode": "source",
                "source": false
              }
            }
          },
          {
            "id": "99a6daa21d1c4e1f",
            "type": "leaf",
            "state": {
              "type": "markdown",
              "state": {
                "file": "mathematics/stochastics/discrete distribution.md",
                "mode": "source",
                "source": false
              }
            }
          },
          {
            "id": "890d329df8b70f69",
            "type": "leaf",
            "state": {
              "type": "markdown",
              "state": {
                "file": "mathematics/stochastics/discrete joint distribution.md",
                "mode": "source",
                "source": false
              }
            }
          }
        ],
        "currentTab": 1
      }
    ],
    "direction": "vertical"
  },
  "left": {
    "id": "52503df592b59803",
    "type": "split",
    "children": [
      {
        "id": "f4b0bf18046f2e17",
        "type": "tabs",
        "children": [
          {
            "id": "8d95cf7e5886b462",
            "type": "leaf",
            "state": {
              "type": "file-explorer",
              "state": {
                "sortOrder": "alphabetical"
              }
            }
          },
          {
            "id": "dc2164f2d3f04496",
            "type": "leaf",
            "state": {
              "type": "search",
              "state": {
                "query": "binomial distribution",
                "matchingCase": true,
                "explainSearch": false,
                "collapseAll": false,
                "extraContext": false,
                "sortOrder": "alphabetical"
              }
            }
          },
          {
            "id": "f3a23b811eb8ab8a",
            "type": "leaf",
            "state": {
              "type": "starred",
              "state": {}
            }
          }
        ]
      }
    ],
    "direction": "horizontal",
    "width": 312.5
  },
  "right": {
    "id": "b4692449453cc2fd",
    "type": "split",
    "children": [
      {
        "id": "38d58c92745d3d60",
        "type": "tabs",
        "children": [
          {
            "id": "659f27a401d45d96",
            "type": "leaf",
            "state": {
              "type": "backlink",
              "state": {
                "file": "mathematics/stochastics/stochastic independent.md",
                "collapseAll": false,
                "extraContext": false,
                "sortOrder": "alphabetical",
                "showSearch": true,
                "searchQuery": "",
                "backlinkCollapsed": false,
                "unlinkedCollapsed": true
              }
            }
          },
          {
            "id": "3ade0cef77700115",
            "type": "leaf",
            "state": {
              "type": "outgoing-link",
              "state": {
                "file": "mathematics/stochastics/stochastic independent.md",
                "linksCollapsed": false,
                "unlinkedCollapsed": true
              }
            }
          },
          {
            "id": "f1f7ce6b64a72d47",
            "type": "leaf",
            "state": {
              "type": "tag",
              "state": {
                "sortOrder": "frequency",
                "useHierarchy": true
              }
            }
          },
          {
            "id": "13e4a1931808b3ee",
            "type": "leaf",
            "state": {
              "type": "outline",
              "state": {
                "file": "mathematics/stochastics/stochastic independent.md"
              }
            }
          }
        ]
      }
    ],
    "direction": "horizontal",
    "width": 300,
    "collapsed": true
  },
  "active": "63374a1eca3db97d",
  "lastOpenFiles": [
    "mathematics/stochastics/joint distribution.md",
    "mathematics/stochastics/probability space.md",
    "mathematics/stochastics/stochastic independent.md",
    "mathematics/stochastics/expected value.md",
    "mathematics/stochastics/marginal distribution.md",
    "mathematics/stochastics/discrete joint distibution.md",
    "mathematics/basics/linear algebra/matrix.md",
    "mathematics/stochastics/sample space.md",
    "mathematics/basics/power set.md",
    "mathematics/stochastics/discrete distribution.md"
  ]
}